{"variables":{"97544":{"years":[],"entities":[],"values":[],"id":97544,"name":"Signed pledges per capita (GCF)","unit":"US$","description":"","createdAt":"2018-06-07T14:42:54.000Z","updatedAt":"2018-06-07T14:42:54.000Z","code":null,"coverage":"","timespan":"","datasetId":2802,"sourceId":15539,"shortUnit":null,"display":{},"columnOrder":0,"originalMetadata":null,"datasetName":"Green Climate Fund Pledges - GCF","s_id":15539,"s_name":"Green Climate Fund Pledges - GCF (2018)","source":{"id":15539,"name":"Green Climate Fund Pledges - GCF (2018)","dataPublishedBy":"Green Climate Fund (GCF)","dataPublisherSource":"","link":"https://www.greenclimate.fund/how-we-work/resource-mobilization","retrievedData":"","additionalInfo":"National pledges towards the Green Climate Fund (GCF). The Green Climate Fund (GCF) is a new global fund created to support the efforts of developing countries to respond to the challenge of climate change. GCF helps developing countries limit or reduce their greenhouse gas (GHG) emissions and adapt to climate change.\n\nGCF is an important part of the UNFCCC Paris climate agreement. Within the Paris Agreement advanced economies have formally agreed to jointly mobilize USD 100 billion per year by 2020.\n\nData reports national pledges as submitted by May 2018."}}},"entityKey":{}}